Workbook

Sheet 접속사 통합
A1: TEPS Reading 9·10번 접속사 통합
A2: 3개 PDF · 16회분 · 32문항의 네 개 보기 전체를 원문 페이지와 대조해 정리했습니다. ‘접속사’에는 접속부사·연결 표현·담화 표지가 포함됩니다.
A3: 고유 표현 | B3: =COUNTA(A6:A63) -> 58 | C3: 전체 보기 | D3: =COUNTA('문항별 보기'!$G$2:$G$129) -> 128 | E3: 분석 문항 | F3: =COUNTIF('문항별 보기'!$I$2:$I$129,"정답") -> 32 | G3: 논리 범주 | H3: =COUNTA('범주별 정리'!$A$6:$A$14) -> 9 | I3: 정답 표기 | J3: 문맥 기준 검토
A5: 연결어 | B5: 논리 관계 | C5: 문법 형태 | D5: 핵심 뜻 | E5: 뉘앙스·사용법 | F5: 영어 예문 | G5: 예문 해석 | H5: 등장 횟수 | I5: 정답 횟수 | J5: 출처 위치
A6: Additionally | B6: 추가 | C6: 접속부사 | D6: 추가로, 게다가 | E6: 중립적이고 비교적 격식 있는 추가. 보통 문장 앞에서 쉼표와 함께 씁니다. | F6: The site is close to transit. Additionally, it has direct access to a public road. | G6: 그 부지는 대중교통과 가깝습니다. 추가로, 공공도로에 직접 접해 있습니다. | H6: =COUNTIF('문항별 보기'!$G$2:$G$129,A6) -> 1 | I6: =COUNTIFS('문항별 보기'!$G$2:$G$129,A6,'문항별 보기'!$I$2:$I$129,"정답") -> 0 | J6: 해커스 기출 T2-Q9(c) · PDF p.19/책 p.85
A7: Further | B7: 추가 | C7: 접속부사 | D7: 더 나아가 | E7: 법률·학술 문체에서 추가 논거를 제시할 때 쓰지만, 일반 문장에서는 furthermore가 더 자연스러운 경우가 많습니다. | F7: The data reveal cost savings. Further, they suggest shorter construction times. | G7: 그 데이터는 비용 절감을 보여 줍니다. 더 나아가, 공사 기간 단축도 시사합니다. | H7: =COUNTIF('문항별 보기'!$G$2:$G$129,A7) -> 1 | I7: =COUNTIFS('문항별 보기'!$G$2:$G$129,A7,'문항별 보기'!$I$2:$I$129,"정답") -> 0 | J7: 시원스쿨 기출 T1-Q10(b) · PDF p.19/책 p.42
A8: Furthermore | B8: 추가 | C8: 접속부사 | D8: 더욱이, 게다가 | E8: 앞 주장에 같은 방향의 강한 근거를 하나 더 보탭니다. 격식 있는 글에 잘 맞습니다. | F8: The modular frame reduces waste. Furthermore, it can be disassembled and reused. | G8: 모듈러 골조는 폐기물을 줄입니다. 더욱이, 해체하여 재사용할 수 있습니다. | H8: =COUNTIF('문항별 보기'!$G$2:$G$129,A8) -> 2 | I8: =COUNTIFS('문항별 보기'!$G$2:$G$129,A8,'문항별 보기'!$I$2:$I$129,"정답") -> 2 | J8: 시원스쿨 기출 T5-Q9(a) · PDF p.155/책 p.178 해커스 실전모의 T4-Q9(d) · PDF p.130/책 p.157
A9: In addition | B9: 추가 | C9: 연결 표현 | D9: 게다가, 또한 | E9: 앞 정보에 별개의 추가 사항을 덧붙이는 가장 무난한 표현입니다. | F9: The proposal meets the height limit. In addition, it preserves the existing trees. | G9: 그 계획안은 높이 제한을 충족합니다. 게다가, 기존 나무도 보존합니다. | H9: =COUNTIF('문항별 보기'!$G$2:$G$129,A9) -> 5 | I9: =COUNTIFS('문항별 보기'!$G$2:$G$129,A9,'문항별 보기'!$I$2:$I$129,"정답") -> 1 | J9: 시원스쿨 기출 T4-Q9(a) · PDF p.121/책 p.144 해커스 기출 T3-Q10(c) · PDF p.53/책 p.119 해커스 기출 T4-Q9(c) · PDF p.85/책 p.153 해커스 실전모의 T3-Q10(a) · PDF p.94/책 p.121 해커스 실전모의 T5-Q10(c) · PDF p.166/책 p.193
A10: Moreover | B10: 추가 | C10: 접속부사 | D10: 더욱이, 게다가 | E10: 앞 주장을 강화하는 추가 근거를 제시합니다. 단순 나열보다 논증적 성격이 강합니다. | F10: The rule is difficult to interpret. Moreover, it varies across districts. | G10: 그 규정은 해석하기 어렵습니다. 더욱이, 지역마다 다르게 적용됩니다. | H10: =COUNTIF('문항별 보기'!$G$2:$G$129,A10) -> 4 | I10: =COUNTIFS('문항별 보기'!$G$2:$G$129,A10,'문항별 보기'!$I$2:$I$129,"정답") -> 0 | J10: 시원스쿨 기출 T1-Q9(b) · PDF p.19/책 p.42 시원스쿨 기출 T2-Q10(b) · PDF p.53/책 p.76 해커스 기출 T5-Q10(a) · PDF p.117/책 p.187 해커스 실전모의 T2-Q9(d) · PDF p.58/책 p.85
A11: What’s more | B11: 추가 | C11: 연결 표현 | D11: 게다가, 더구나 | E11: 강조가 느껴지는 추가 표현으로, moreover보다 대화체에 가깝습니다. | F11: The unit is affordable. What’s more, it can be installed in a single day. | G11: 그 유닛은 가격이 합리적입니다. 게다가, 하루 만에 설치할 수 있습니다. | H11: =COUNTIF('문항별 보기'!$G$2:$G$129,A11) -> 1 | I11: =COUNTIFS('문항별 보기'!$G$2:$G$129,A11,'문항별 보기'!$I$2:$I$129,"정답") -> 0 | J11: 해커스 실전모의 T6-Q10(a) · PDF p.202/책 p.229
A12: Accordingly | B12: 인과·결과 | C12: 접속부사 | D12: 그에 따라, 따라서 | E12: 앞 사실에 맞추어 취한 조치나 논리적 결과를 나타냅니다. | F12: The parcel lacks legal road access. Accordingly, it was removed from the shortlist. | G12: 그 필지는 법적 도로 접면이 없습니다. 그에 따라, 후보 목록에서 제외되었습니다. | H12: =COUNTIF('문항별 보기'!$G$2:$G$129,A12) -> 3 | I12: =COUNTIFS('문항별 보기'!$G$2:$G$129,A12,'문항별 보기'!$I$2:$I$129,"정답") -> 2 | J12: 시원스쿨 기출 T4-Q10(d) · PDF p.121/책 p.144 해커스 실전모의 T2-Q10(d) · PDF p.58/책 p.85 해커스 실전모의 T4-Q10(a) · PDF p.130/책 p.157
A13: As a result | B13: 인과·결과 | C13: 연결 표현 | D13: 그 결과 | E13: 앞 사건의 직접적인 결과를 명확하게 제시합니다. | F13: The joint failed the load test. As a result, the team revised its geometry. | G13: 접합부가 하중 시험을 통과하지 못했습니다. 그 결과, 팀은 형상을 수정했습니다. | H13: =COUNTIF('문항별 보기'!$G$2:$G$129,A13) -> 1 | I13: =COUNTIFS('문항별 보기'!$G$2:$G$129,A13,'문항별 보기'!$I$2:$I$129,"정답") -> 1 | J13: 해커스 기출 T2-Q10(b) · PDF p.19/책 p.85
A14: Consequently | B14: 인과·결과 | C14: 접속부사 | D14: 그 결과, 따라서 | E14: 원인에서 자연스럽게 파생되는 결과를 격식 있게 연결합니다. | F14: Material prices rose sharply. Consequently, the original budget became unrealistic. | G14: 자재 가격이 크게 올랐습니다. 그 결과, 기존 예산은 비현실적이 되었습니다. | H14: =COUNTIF('문항별 보기'!$G$2:$G$129,A14) -> 3 | I14: =COUNTIFS('문항별 보기'!$G$2:$G$129,A14,'문항별 보기'!$I$2:$I$129,"정답") -> 1 | J14: 시원스쿨 기출 T5-Q10(d) · PDF p.155/책 p.178 해커스 실전모의 T4-Q9(b) · PDF p.130/책 p.157 해커스 실전모의 T5-Q9(c) · PDF p.166/책 p.193
A15: For this reason | B15: 인과·결과 | C15: 연결 표현 | D15: 이러한 이유로 | E15: 앞 문장 전체를 이유로 받아 뒤 판단이나 행동을 제시합니다. | F15: The area floods every summer. For this reason, critical equipment was placed above ground level. | G15: 그 지역은 매년 여름 침수됩니다. 이러한 이유로, 핵심 장비를 지상층보다 높게 배치했습니다. | H15: =COUNTIF('문항별 보기'!$G$2:$G$129,A15) -> 2 | I15: =COUNTIFS('문항별 보기'!$G$2:$G$129,A15,'문항별 보기'!$I$2:$I$129,"정답") -> 2 | J15: 시원스쿨 기출 T3-Q9(b) · PDF p.87/책 p.110 해커스 기출 T3-Q10(b) · PDF p.53/책 p.119
A16: Given that fact | B16: 인과·결과 | C16: 연결 표현 | D16: 그 사실을 고려하면 | E16: 이미 제시된 사실을 판단의 전제로 삼을 때 씁니다. | F16: The site lies in a flood-risk zone. Given that fact, the foundation scheme needs revision. | G16: 그 부지는 침수 위험 구역에 있습니다. 그 사실을 고려하면, 기초 계획을 수정해야 합니다. | H16: =COUNTIF('문항별 보기'!$G$2:$G$129,A16) -> 1 | I16: =COUNTIFS('문항별 보기'!$G$2:$G$129,A16,'문항별 보기'!$I$2:$I$129,"정답") -> 0 | J16: 해커스 실전모의 T5-Q10(d) · PDF p.166/책 p.193
A17: Hence | B17: 인과·결과 | C17: 접속부사 | D17: 따라서, 그러므로 | E17: 논리적으로 도출되는 결론을 간결하고 격식 있게 나타냅니다. | F17: The modules share the same interface; hence, they can be rearranged without redesign. | G17: 모듈들은 같은 인터페이스를 공유합니다. 따라서, 재설계 없이 재배치할 수 있습니다. | H17: =COUNTIF('문항별 보기'!$G$2:$G$129,A17) -> 1 | I17: =COUNTIFS('문항별 보기'!$G$2:$G$129,A17,'문항별 보기'!$I$2:$I$129,"정답") -> 1 | J17: 해커스 실전모의 T2-Q9(a) · PDF p.58/책 p.85
... A63: Of course | B63: 강조·근거 | C63: 담화 표지 | D63: 물론 | E63: 공유된 사실을 인정하거나 당연한 점을 강조합니다. 뒤에 제한·대조가 이어지기도 합니다. | F63: Of course, digital automation does not eliminate the need for professional judgment. | G63: 물론, 디지털 자동화가 전문적인 판단의 필요성을 없애는 것은 아닙니다. | H63: =COUNTIF('문항별 보기'!$G$2:$G$129,A63) -> 1 | I63: =COUNTIFS('문항별 보기'!$G$2:$G$129,A63,'문항별 보기'!$I$2:$I$129,"정답") -> 0 | J63: 해커스 기출 T2-Q9(a) · PDF p.19/책 p.85

Sheet 문항별 보기
A1: 자료 | B1: 회차 | C1: PDF 페이지 | D1: 책 페이지 | E1: 문항 | F1: 보기 | G1: 연결어 | H1: 논리 관계 | I1: 정답 여부
A2: 시원스쿨 기출 | B2: TEST 1 | C2: 19 | D2: 42 | E2: 9 | F2: a | G2: Granted | H2: 대조·양보 | I2: 오답
A3: 시원스쿨 기출 | B3: TEST 1 | C3: 19 | D3: 42 | E3: 9 | F3: b | G3: Moreover | H3: 추가 | I3: 오답
A4: 시원스쿨 기출 | B4: TEST 1 | C4: 19 | D4: 42 | E4: 9 | F4: c | G4: For all that | H4: 대조·양보 | I4: 오답
A5: 시원스쿨 기출 | B5: TEST 1 | C5: 19 | D5: 42 | E5: 9 | F5: d | G5: For example | H5: 예시·구체화 | I5: 정답
A6: 시원스쿨 기출 | B6: TEST 1 | C6: 19 | D6: 42 | E6: 10 | F6: a | G6: Thus | H6: 인과·결과 | I6: 정답
A7: 시원스쿨 기출 | B7: TEST 1 | C7: 19 | D7: 42 | E7: 10 | F7: b | G7: Further | H7: 추가 | I7: 오답
A8: 시원스쿨 기출 | B8: TEST 1 | C8: 19 | D8: 42 | E8: 10 | F8: c | G8: Likewise | H8: 유사·병렬 | I8: 오답
A9: 시원스쿨 기출 | B9: TEST 1 | C9: 19 | D9: 42 | E9: 10 | F9: d | G9: Regardless | H9: 대조·양보 | I9: 오답
A10: 시원스쿨 기출 | B10: TEST 2 | C10: 53 | D10: 76 | E10: 9 | F10: a | G10: Likewise | H10: 유사·병렬 | I10: 오답
A11: 시원스쿨 기출 | B11: TEST 2 | C11: 53 | D11: 76 | E11: 9 | F11: b | G11: Similarly | H11: 유사·병렬 | I11: 오답
A12: 시원스쿨 기출 | B12: TEST 2 | C12: 53 | D12: 76 | E12: 9 | F12: c | G12: Ultimately | H12: 바꿔 말하기·요약 | I12: 정답
A13: 시원스쿨 기출 | B13: TEST 2 | C13: 53 | D13: 76 | E13: 9 | F13: d | G13: Nonetheless | H13: 대조·양보 | I13: 오답
... A129: 해커스 실전모의 | B129: TEST 6 | C129: 202 | D129: 229 | E129: 10 | F129: d | G129: In other words | H129: 바꿔 말하기·요약 | I129: 정답

Sheet 범주별 정리
A1: 논리 관계별 빠른 판단 가이드
A2: 빈칸 앞뒤의 논리 방향을 먼저 정한 뒤, 같은 범주 안에서 뉘앙스와 문법 형태를 비교하면 빠르게 소거할 수 있습니다.
A5: 논리 관계 | B5: 판단 질문 | C5: 대표 표현 | D5: 고유 표현 수 | E5: 전체 등장 수 | F5: 학습 포인트
A6: 추가 | B6: 같은 방향의 정보를 더하는가? | C6: Additionally, Further, Furthermore, In addition | D6: =COUNTIF('접속사 통합'!$B$6:$B$63,A6) -> 6 | E6: =COUNTIF('문항별 보기'!$H$2:$H$129,A6) -> 14 | F6: 앞 문장을 지지하거나 내용을 한 단계 더 보탤 때 씁니다.
A7: 인과·결과 | B7: 앞 내용 때문에 뒤 결과가 나오는가? | C7: Accordingly, As a result, Consequently, For this reason | D7: =COUNTIF('접속사 통합'!$B$6:$B$63,A7) -> 8 | E7: =COUNTIF('문항별 보기'!$H$2:$H$129,A7) -> 15 | F7: 원인 → 결과의 방향이 맞는지 먼저 확인합니다.
A8: 대조·양보 | B8: 예상과 반대이거나 두 관점을 대비하는가? | C8: Admittedly, At the same time, Conversely, Despite this | D8: =COUNTIF('접속사 통합'!$B$6:$B$63,A8) -> 16 | E8: =COUNTIF('문항별 보기'!$H$2:$H$129,A8) -> 41 | F8: 단순 대조와 '그럼에도 불구하고'의 양보를 구분합니다.
A9: 예시·구체화 | B9: 일반 진술을 사례나 정확한 내용으로 좁히는가? | C9: Especially, For example, For instance, In particular | D9: =COUNTIF('접속사 통합'!$B$6:$B$63,A9) -> 7 | E9: =COUNTIF('문항별 보기'!$H$2:$H$129,A9) -> 15 | F9: 예시(for example)와 정확한 재명명(namely)을 구별합니다.
A10: 유사·병렬 | B10: 앞 내용과 비슷한 사례나 논리를 잇는가? | C10: In the same sense, Likewise, Similarly | D10: =COUNTIF('접속사 통합'!$B$6:$B$63,A10) -> 3 | E10: =COUNTIF('문항별 보기'!$H$2:$H$129,A10) -> 8 | F10: 두 문장의 방향과 문법 구조가 평행한지 확인합니다.
A11: 바꿔 말하기·요약 | B11: 앞 내용을 다시 표현하거나 압축하는가? | C11: In conclusion, In effect, In essence, In fact | D11: =COUNTIF('접속사 통합'!$B$6:$B$63,A11) -> 8 | E11: =COUNTIF('문항별 보기'!$H$2:$H$129,A11) -> 15 | F11: 설명·재진술·최종 요약 중 어떤 기능인지 구분합니다.
A12: 시간·순서 | B12: 사건의 시점이나 전개 순서를 나타내는가? | C12: In the first place, Meanwhile, Subsequently, Thereafter | D12: =COUNTIF('접속사 통합'!$B$6:$B$63,A12) -> 5 | E12: =COUNTIF('문항별 보기'!$H$2:$H$129,A12) -> 10 | F12: 동시성, 이후, 시작, 우선순위를 시간축으로 그려 봅니다.
A13: 대안·조건 | B13: 다른 선택지나 그렇지 않을 경우를 제시하는가? | C13: Alternately, Alternatively, Otherwise | D13: =COUNTIF('접속사 통합'!$B$6:$B$63,A13) -> 3 | E13: =COUNTIF('문항별 보기'!$H$2:$H$129,A13) -> 8 | F13: alternately(교대로)와 alternatively(대안으로)를 특히 구별합니다.
A14: 강조·근거 | B14: 앞 판단을 강조하거나 이유를 보충하는가? | C14: After all, Of course | D14: =COUNTIF('접속사 통합'!$B$6:$B$63,A14) -> 2 | E14: =COUNTIF('문항별 보기'!$H$2:$H$129,A14) -> 2 | F14: 새 정보보다 필자의 태도와 정당화 기능에 주목합니다.
A17: 자주 헷갈리는 표현
A18: 표현 A | B18: 표현 B | C18: 핵심 차이 | D18: 판단 예시
A19: Alternately | B19: Alternatively | C19: 교대로·번갈아 / 다른 대안으로는 | D19: 두 작업팀이 번갈아 일함 / 다른 설계안을 제시함
A20: On the contrary | B20: On the other hand | C20: 앞 진술을 부정·정정 / 두 측면을 균형 있게 대조 | D20: 느려지지 않았다. 오히려 빨라졌다 / 장점이 있다. 반면 단점도 있다
A21: Namely | B21: For example | C21: 정확히 무엇인지 특정 / 여러 사례 중 하나를 예시 | D21: 두 특성, 즉 A와 B / 여러 규정, 예를 들어 높이 제한
A22: Despite this | B22: Even though | C22: 문장 연결 표현 / 뒤에 절을 이끄는 종속접속사 | D22: Despite this, S+V / Even though S+V, S+V
A23: Subsequently | B23: Thereafter | C23: 그 다음 사건 / 그 시점 이후의 지속·전개 | D23: 그 후 새 이름을 얻음 / 처음 5분 뒤부터 계속 과금
A24: Admittedly | B24: Granted | C24: 격식 있는 사실 인정 / 상대 주장의 일부를 인정 | D24: 인정하건대 비용이 높다 / 물론 배우기 어렵다는 점은 인정한다
